tp_sql/main.py
tp_sql-0.0.1.dist-info/METADATA
tp_sql-0.0.1.dist-info/WHEEL
tp_sql-0.0.1.dist-info/top_level.txt
tp_sql-0.0.1.dist-info/RECORD
