Metadata-Version: 2.1
Name: tp_sql
Version: 0.0.1
Requires-Dist: requests
